verify_data/__init__.py
verify_data/verify.py
verifydata-0.0.8.dist-info/LICENSE
verifydata-0.0.8.dist-info/METADATA
verifydata-0.0.8.dist-info/WHEEL
verifydata-0.0.8.dist-info/RECORD
