Metadata-Version: 2.1
Name: VerifyData
Version: 0.0.8
Summary: VerifyData is an intuitive library focused on data quality assessment, offering automated checks for completeness, consistency, and accuracy to guarantee high standards across your data flows.
License: MIT
Author: developerdatascience
Author-email: harendra263@gmail.com
Requires-Python: >=3.9
Classifier: License :: OSI Approved :: MIT License
Classifier: Programming Language :: Python :: 3
Classifier: Programming Language :: Python :: 3.9
Classifier: Programming Language :: Python :: 3.10
Classifier: Programming Language :: Python :: 3.11
Classifier: Programming Language :: Python :: 3.12
Classifier: Programming Language :: Python :: 3.13
Requires-Dist: click (>=8.1.0,<9.0.0)
Requires-Dist: ipykernel (==6.5.0)
Requires-Dist: notebook (>=6.5.5,<7.0.0)
Requires-Dist: pyspark (>=3.5.3,<4.0.0)
